TOPSIS_101703317/Topsis.py
topsis3317-1.1.0.dist-info/LICENSE.txt
topsis3317-1.1.0.dist-info/METADATA
topsis3317-1.1.0.dist-info/WHEEL
topsis3317-1.1.0.dist-info/entry_points.txt
topsis3317-1.1.0.dist-info/top_level.txt
topsis3317-1.1.0.dist-info/RECORD
