Metadata-Version: 2.1
Name: topsis3317
Version: 1.1.0
Summary: A Python package for topsis analysis.
Home-page: https://github.com/manaskhatri/Topsis
Author: Manas Khatri
Author-email: manaskhatri4534@gmail.com
License: MIT
Platform: UNKNOWN
Classifier: License :: OSI Approved :: MIT License
Classifier: Programming Language :: Python :: 3
Classifier: Programming Language :: Python :: 3.7
Requires-Dist: requests
